rule/__init__.py
rule/op.py
rule-0.1.1.dist-info/LICENSE.txt
rule-0.1.1.dist-info/METADATA
rule-0.1.1.dist-info/WHEEL
rule-0.1.1.dist-info/entry_points.txt
rule-0.1.1.dist-info/top_level.txt
rule-0.1.1.dist-info/RECORD
