Metadata-Version: 2.1
Name: rule
Version: 0.1.1
Summary: A rule engine written in python.
Home-page: https://github.com/tclh123/rule
Author: Harry Lee
Author-email: tclh123@gmail.com
License: MIT
Keywords: rule
Platform: UNKNOWN
Classifier: Programming Language :: Python
Classifier: Development Status :: 5 - Production/Stable
Classifier: Environment :: Console
Classifier: Intended Audience :: Developers
Classifier: License :: OSI Approved :: MIT License
Classifier: Operating System :: OS Independent
Classifier: Topic :: Software Development :: Libraries :: Python Modules
